{"13Ref.png5150231":{"filename":"13Ref.png","size":5150231,"regions":[{"shape_attributes":{"name":"polygon","all_points_x":[1659,1730,1785,1651,1622],"all_points_y":[252,246,282,298,260]},"region_attributes":{"Object":"A1"}},{"shape_attributes":{"name":"polygon","all_points_x":[1643,1789,1813,1670],"all_points_y":[331,313,352,370]},"region_attributes":{"Object":"A2"}},{"shape_attributes":{"name":"polygon","all_points_x":[1661,1686,1826,1799],"all_points_y":[424,467,424,389]},"region_attributes":{"Object":"A3"}},{"shape_attributes":{"name":"polygon","all_points_x":[1678,1694,1846,1826],"all_points_y":[527,586,518,472]},"region_attributes":{"Object":"A4"}},{"shape_attributes":{"name":"polygon","all_points_x":[1726,1743,1889,1870],"all_points_y":[611,680,586,533]},"region_attributes":{"Object":"A5"}},{"shape_attributes":{"name":"polygon","all_points_x":[1738,1753,1898,1886],"all_points_y":[734,796,673,625]},"region_attributes":{"Object":"A6"}},{"shape_attributes":{"name":"polygon","all_points_x":[1778,1791,1936,1921],"all_points_y":[845,907,756,711]},"region_attributes":{"Object":"A7"}},{"shape_attributes":{"name":"polygon","all_points_x":[1802,1812,1944,1930],"all_points_y":[976,1031,903,844]},"region_attributes":{"Object":"A8"}},{"shape_attributes":{"name":"polygon","all_points_x":[751,1007,999,743],"all_points_y":[59,48,92,99]},"region_attributes":{"Object":"C1"}},{"shape_attributes":{"name":"polygon","all_points_x":[1158,1384,1388,1165],"all_points_y":[135,149,189,178]},"region_attributes":{"Object":"B1"}},{"shape_attributes":{"name":"polygon","all_points_x":[745,985,971,719],"all_points_y":[123,117,158,168]},"region_attributes":{"Object":"C2"}},{"shape_attributes":{"name":"polygon","all_points_x":[1150,1367,1370,1150],"all_points_y":[217,226,273,260]},"region_attributes":{"Object":"B2"}},{"shape_attributes":{"name":"polygon","all_points_x":[1158,1373,1369,1152],"all_points_y":[316,321,387,380]},"region_attributes":{"Object":"B3"}},{"shape_attributes":{"name":"polygon","all_points_x":[1143,1378,1380,1129],"all_points_y":[452,453,563,567]},"region_attributes":{"Object":"B4"}},{"shape_attributes":{"name":"polygon","all_points_x":[1106,1367,1367,1093],"all_points_y":[625,619,748,760]},"region_attributes":{"Object":"B5"}},{"shape_attributes":{"name":"polygon","all_points_x":[539,1004,1002,541],"all_points_y":[520,525,592,592]},"region_attributes":{"Object":"C6"}},{"shape_attributes":{"name":"polygon","all_points_x":[584,969,957,569],"all_points_y":[376,373,453,439]},"region_attributes":{"Object":"C5"}},{"shape_attributes":{"name":"polygon","all_points_x":[638,967,960,622],"all_points_y":[286,272,319,335]},"region_attributes":{"Object":"C4"}},{"shape_attributes":{"name":"polygon","all_points_x":[693,961,957,678],"all_points_y":[193,187,228,237]},"region_attributes":{"Object":"C3"}},{"shape_attributes":{"name":"polygon","all_points_x":[169,304,291,158],"all_points_y":[290,226,261,329]},"region_attributes":{"Object":"D1"}},{"shape_attributes":{"name":"polygon","all_points_x":[140,286,257,123],"all_points_y":[372,309,351,403]},"region_attributes":{"Object":"D2"}},{"shape_attributes":{"name":"polygon","all_points_x":[17,172,150,9],"all_points_y":[618,572,628,665]},"region_attributes":{"Object":"D5"}},{"shape_attributes":{"name":"polygon","all_points_x":[54,231,216,41],"all_points_y":[530,468,523,577]},"region_attributes":{"Object":"D4"}},{"shape_attributes":{"name":"polygon","all_points_x":[96,254,235,86],"all_points_y":[447,390,435,488]},"region_attributes":{"Object":"D3"}},{"shape_attributes":{"name":"polygon","all_points_x":[491,985,970,452],"all_points_y":[662,670,767,744]},"region_attributes":{"Object":"C7"}},{"shape_attributes":{"name":"polygon","all_points_x":[0,187,440,580,300,1452,1438,1566,1644,2012,1989,1823,1553,1029,660,648,434,397,189,14],"all_points_y":[695,669,146,126,817,932,121,148,1111,1070,545,214,130,33,47,101,126,189,216,551]},"region_attributes":{"Object":"Mask"}}],"file_attributes":{}}}