{"42Ref.png5546182":{"filename":"42Ref.png","size":4017205,"regions":[{"shape_attributes":{"name":"polygon","all_points_x":[820,818,1119,1097,778],"all_points_y":[1183,1183,1156,1285,1283]},"region_attributes":{"Object":"A11"}},{"shape_attributes":{"name":"polygon","all_points_x":[846,1458,1445,815],"all_points_y":[1032,947,1075,1154]},"region_attributes":{"Object":"A10"}},{"shape_attributes":{"name":"polygon","all_points_x":[898,1482,1462,868],"all_points_y":[859,776,890,966]},"region_attributes":{"Object":"A9"}},{"shape_attributes":{"name":"polygon","all_points_x":[929,1484,1482,907],"all_points_y":[706,651,739,802]},"region_attributes":{"Object":"A8"}},{"shape_attributes":{"name":"polygon","all_points_x":[944,1491,1493,962],"all_points_y":[647,586,540,601]},"region_attributes":{"Object":"A7"}},{"shape_attributes":{"name":"polygon","all_points_x":[999,1486,1486,977],"all_points_y":[498,448,498,553]},"region_attributes":{"Object":"A6"}},{"shape_attributes":{"name":"polygon","all_points_x":[1025,1473,1476,1014],"all_points_y":[417,376,415,452]},"region_attributes":{"Object":"A5"}},{"shape_attributes":{"name":"polygon","all_points_x":[1047,1458,1460,1045],"all_points_y":[325,297,328,363]},"region_attributes":{"Object":"A4"}},{"shape_attributes":{"name":"polygon","all_points_x":[1069,1432,1434,1062],"all_points_y":[258,225,260,284]},"region_attributes":{"Object":"A3"}},{"shape_attributes":{"name":"polygon","all_points_x":[1095,1408,1408,1086],"all_points_y":[201,175,203,225]},"region_attributes":{"Object":"A2"}},{"shape_attributes":{"name":"polygon","all_points_x":[1108,1364,1362,1097],"all_points_y":[155,140,160,186]},"region_attributes":{"Object":"A1"}},{"shape_attributes":{"name":"polygon","all_points_x":[483,518,588,562],"all_points_y":[472,422,612,671]},"region_attributes":{"Object":"B6"}},{"shape_attributes":{"name":"polygon","all_points_x":[542,573,634,603],"all_points_y":[402,363,529,588]},"region_attributes":{"Object":"B5"}},{"shape_attributes":{"name":"polygon","all_points_x":[581,581,651,686,610],"all_points_y":[345,348,505,452,315]},"region_attributes":{"Object":"B4"}},{"shape_attributes":{"name":"polygon","all_points_x":[616,702,726,645],"all_points_y":[295,435,391,273]},"region_attributes":{"Object":"B3"}},{"shape_attributes":{"name":"polygon","all_points_x":[759,680,654,732],"all_points_y":[334,227,256,374]},"region_attributes":{"Object":"B2"}},{"shape_attributes":{"name":"polygon","all_points_x":[708,791,767,686],"all_points_y":[195,280,313,214]},"region_attributes":{"Object":"B1"}},{"shape_attributes":{"name":"polygon","all_points_x":[509,540,472,439],"all_points_y":[785,717,503,551]},"region_attributes":{"Object":"B7"}},{"shape_attributes":{"name":"polygon","all_points_x":[398,446,398,354],"all_points_y":[931,892,640,678]},"region_attributes":{"Object":"B9"}},{"shape_attributes":{"name":"polygon","all_points_x":[339,407,330,293],"all_points_y":[979,1004,680,719]},"region_attributes":{"Object":"B10"}},{"shape_attributes":{"name":"polygon","all_points_x":[400,428,503,470],"all_points_y":[614,562,804,872]},"region_attributes":{"Object":"B8"}},{"shape_attributes":{"name":"polygon","all_points_x":[315,269,498,697,1447,1524,1517,1493,756,404],"all_points_y":[973,717,380,173,120,577,1172,1292,1288,1152]},"region_attributes":{"Object":"Mask"}}],"file_attributes":{}}}