{"59Ref.png3867672":{"filename":"59Ref.png","size":3867672,"regions":[{"shape_attributes":{"name":"polygon","all_points_x":[1200,1221,1226,1206],"all_points_y":[272,272,291,291]},"region_attributes":{"Object":"A1"}},{"shape_attributes":{"name":"polygon","all_points_x":[1241,1262,1271,1248],"all_points_y":[271,269,301,301]},"region_attributes":{"Object":"A2"}},{"shape_attributes":{"name":"polygon","all_points_x":[1281,1302,1318,1293],"all_points_y":[284,284,315,317]},"region_attributes":{"Object":"A3"}},{"shape_attributes":{"name":"polygon","all_points_x":[1326,1349,1364,1339],"all_points_y":[308,308,354,354]},"region_attributes":{"Object":"A4"}},{"shape_attributes":{"name":"polygon","all_points_x":[1377,1400,1431,1407],"all_points_y":[333,335,376,376]},"region_attributes":{"Object":"A5"}},{"shape_attributes":{"name":"polygon","all_points_x":[1436,1463,1500,1476],"all_points_y":[363,363,403,399]},"region_attributes":{"Object":"A6"}},{"shape_attributes":{"name":"polygon","all_points_x":[1510,1533,1559,1539],"all_points_y":[391,400,438,438]},"region_attributes":{"Object":"A7"}},{"shape_attributes":{"name":"polygon","all_points_x":[1570,1585,1617,1599],"all_points_y":[436,434,488,487]},"region_attributes":{"Object":"A8"}},{"shape_attributes":{"name":"polygon","all_points_x":[1627,1646,1684,1667],"all_points_y":[458,458,498,498]},"region_attributes":{"Object":"A9"}},{"shape_attributes":{"name":"polygon","all_points_x":[1693,1711,1753,1731],"all_points_y":[480,480,524,524]},"region_attributes":{"Object":"A10"}},{"shape_attributes":{"name":"polygon","all_points_x":[1008,1144,1178,1036],"all_points_y":[540,458,473,561]},"region_attributes":{"Object":"B1"}},{"shape_attributes":{"name":"polygon","all_points_x":[1068,1213,1245,1105],"all_points_y":[609,511,523,631]},"region_attributes":{"Object":"B2"}},{"shape_attributes":{"name":"polygon","all_points_x":[1137,1265,1304,1186],"all_points_y":[673,552,581,698]},"region_attributes":{"Object":"B3"}},{"shape_attributes":{"name":"polygon","all_points_x":[1216,1326,1366,1256],"all_points_y":[730,594,613,761]},"region_attributes":{"Object":"B4"}},{"shape_attributes":{"name":"polygon","all_points_x":[1284,1402,1439,1342],"all_points_y":[802,641,670,832]},"region_attributes":{"Object":"B5"}},{"shape_attributes":{"name":"polygon","all_points_x":[1368,1457,1508,1435],"all_points_y":[889,695,724,911]},"region_attributes":{"Object":"B6"}},{"shape_attributes":{"name":"polygon","all_points_x":[1527,1581,1537,1482],"all_points_y":[751,775,946,922]},"region_attributes":{"Object":"B7"}},{"shape_attributes":{"name":"polygon","all_points_x":[1605,1657,1610,1557],"all_points_y":[830,859,1062,1031]},"region_attributes":{"Object":"B8"}},{"shape_attributes":{"name":"polygon","all_points_x":[1685,1735,1714,1649],"all_points_y":[881,905,1084,1064]},"region_attributes":{"Object":"B9"}},{"shape_attributes":{"name":"polygon","all_points_x":[1771,1818,1794,1739],"all_points_y":[962,981,1195,1176]},"region_attributes":{"Object":"B10"}},{"shape_attributes":{"name":"polygon","all_points_x":[1851,1903,1896,1847],"all_points_y":[1000,1020,1213,1199]},"region_attributes":{"Object":"B11"}},{"shape_attributes":{"name":"polygon","all_points_x":[1932,1966,1958,1928],"all_points_y":[1065,1088,1253,1238]},"region_attributes":{"Object":"B12"}},{"shape_attributes":{"name":"polygon","all_points_x":[1997,2032,2027,1988],"all_points_y":[1128,1145,1279,1272]},"region_attributes":{"Object":"B13"}},{"shape_attributes":{"name":"polygon","all_points_x":[2015,2052,2052,1640,1263,943,943,1135,1224,1756,2012,1804,1566,1398,1181,1176,1230,1329,1489,1637,1715,1782,1807,2006],"all_points_y":[949,1150,1292,1294,962,631,536,427,445,785,949,657,516,422,323,253,248,276,354,427,472,554,658,939]},"region_attributes":{"Object":"Mask"}}],"file_attributes":{}}}